{
  "app_name": "subscriptions",
  "src_hash": "e1d818b6b77c232250f265fa9933ab389cce26c1",
  "src_tag": "",
  "src_branch": "qa",
  "patternfly_dependencies": ["@patternfly/patternfly@4.50.4","@patternfly/react-charts@6.11.7","@patternfly/react-core@4.63.3","@patternfly/react-icons@4.7.11","@patternfly/react-styles@4.7.8","@patternfly/react-table@4.19.5","@patternfly/react-tokens@4.9.12"],
  "travis": {
    "event_type": "push",
    "build_number": "1393",
    "build_web_url": "https://travis-ci.com/RedHatInsights/curiosity-frontend/builds/202798793"
  }
}
